{
  "tabPane": [
    {
      "title": "SmartDashboard",
      "autoPopulate": true,
      "autoPopulatePrefix": "SmartDashboard/",
      "widgetPane": {
        "gridSize": 128.0,
        "showGrid": true,
        "hgap": 16.0,
        "vgap": 16.0,
        "tiles": {
          "0,0": {
            "size": [
              1,
              1
            ],
            "content": {
              "_type": "Text View",
              "_source0": "network_table:///SmartDashboard/Shooter_Speed",
              "_title": "Shooter_Speed"
            }
          },
          "1,0": {
            "size": [
              1,
              1
            ],
            "content": {
              "_type": "ComboBox Chooser",
              "_source0": "network_table:///SmartDashboard/Drive Mode",
              "_title": "Drive Mode"
            }
          },
          "2,0": {
            "size": [
              1,
              1
            ],
            "content": {
              "_type": "ComboBox Chooser",
              "_source0": "network_table:///SmartDashboard/Auto Delay",
              "_title": "Auto Delay"
            }
          },
          "3,0": {
            "size": [
              1,
              1
            ],
            "content": {
              "_type": "ComboBox Chooser",
              "_source0": "network_table:///SmartDashboard/Auton choices",
              "_title": "Auton choices"
            }
          },
          "4,0": {
            "size": [
              1,
              1
            ],
            "content": {
              "_type": "Text View",
              "_source0": "network_table:///SmartDashboard/Battery_Voltage",
              "_title": "Battery_Voltage"
            }
          },
          "5,0": {
            "size": [
              1,
              1
            ],
            "content": {
              "_type": "Text View",
              "_source0": "network_table:///SmartDashboard/Venom_RearRight",
              "_title": "Venom_RearRight"
            }
          },
          "6,0": {
            "size": [
              1,
              1
            ],
            "content": {
              "_type": "Text View",
              "_source0": "network_table:///SmartDashboard/Venom_RearLeft",
              "_title": "Venom_RearLeft"
            }
          },
          "7,0": {
            "size": [
              1,
              1
            ],
            "content": {
              "_type": "Text View",
              "_source0": "network_table:///SmartDashboard/RoboRio",
              "_title": "RoboRio"
            }
          },
          "8,0": {
            "size": [
              1,
              1
            ],
            "content": {
              "_type": "Text View",
              "_source0": "network_table:///SmartDashboard/Venom_FrontRight",
              "_title": "Venom_FrontRight"
            }
          },
          "9,0": {
            "size": [
              1,
              1
            ],
            "content": {
              "_type": "Text View",
              "_source0": "network_table:///SmartDashboard/Shooter_Output_Current ",
              "_title": "Shooter_Output_Current "
            }
          },
          "10,0": {
            "size": [
              1,
              1
            ],
            "content": {
              "_type": "Text View",
              "_source0": "network_table:///SmartDashboard/Shooter_Temperature",
              "_title": "Shooter_Temperature"
            }
          },
          "11,0": {
            "size": [
              1,
              1
            ],
            "content": {
              "_type": "Text View",
              "_source0": "network_table:///SmartDashboard/Venom_FrontLeft",
              "_title": "Venom_FrontLeft"
            }
          },
          "12,0": {
            "size": [
              1,
              1
            ],
            "content": {
              "_type": "Text View",
              "_source0": "network_table:///SmartDashboard/Shooter_Speed_Graph",
              "_title": "Shooter_Speed_Graph"
            }
          },
          "0,1": {
            "size": [
              2,
              1
            ],
            "content": {
              "_type": "Text View",
              "_source0": "network_table:///SmartDashboard/Shooter_Output_Voltage ",
              "_title": "Shooter_Output_Voltage "
            }
          }
        }
      }
    },
    {
      "title": "LiveWindow",
      "autoPopulate": true,
      "autoPopulatePrefix": "LiveWindow/",
      "widgetPane": {
        "gridSize": 128.0,
        "showGrid": true,
        "hgap": 16.0,
        "vgap": 16.0,
        "tiles": {
          "0,0": {
            "size": [
              5,
              5
            ],
            "content": {
              "_type": "Subsystem Layout",
              "_source0": "network_table:///LiveWindow/Ungrouped",
              "_title": "Ungrouped",
              "Layout/Label position": "BOTTOM",
              "_children": [
                {
                  "_type": "PDP",
                  "_source0": "network_table:///LiveWindow/Ungrouped/PowerDistributionPanel[0]",
                  "_title": "PowerDistributionPanel[0]",
                  "Visuals/Show voltage and current values": true
                },
                {
                  "_type": "Differential Drivebase",
                  "_source0": "network_table:///LiveWindow/Ungrouped/DifferentialDrive[1]",
                  "_title": "DifferentialDrive[1]",
                  "Wheels/Number of wheels": 4,
                  "Wheels/Wheel diameter": 80.0,
                  "Visuals/Show velocity vectors": true
                }
              ]
            }
          }
        }
      }
    },
    {
      "title": "Shooter",
      "autoPopulate": false,
      "autoPopulatePrefix": "",
      "widgetPane": {
        "gridSize": 128.0,
        "showGrid": true,
        "hgap": 16.0,
        "vgap": 16.0,
        "tiles": {
          "9,4": {
            "size": [
              1,
              1
            ],
            "content": {
              "_type": "Text View",
              "_source0": "network_table:///SmartDashboard/Shooter_Output_Current ",
              "_title": "Output_Current "
            }
          },
          "10,4": {
            "size": [
              1,
              1
            ],
            "content": {
              "_type": "Text View",
              "_source0": "network_table:///SmartDashboard/Shooter_Output_Voltage ",
              "_title": "Output_Voltage "
            }
          },
          "0,4": {
            "size": [
              1,
              1
            ],
            "content": {
              "_type": "Text View",
              "_source0": "network_table:///SmartDashboard/Shooter_Speed",
              "_title": "Speed"
            }
          },
          "0,0": {
            "size": [
              11,
              4
            ],
            "content": {
              "_type": "Graph",
              "_source0": "network_table:///SmartDashboard/Shooter_Speed_Graph",
              "_title": "Shooter_Speed",
              "Graph/Visible time": 30.0,
              "Y-axis/Automatic bounds": true,
              "Y-axis/Upper bound": 1.0,
              "Y-axis/Lower bound": -1.0,
              "Visible data/SmartDashboard/Shooter_Speed_Graph": true
            }
          },
          "1,4": {
            "size": [
              1,
              1
            ],
            "content": {
              "_type": "Text View",
              "_source0": "network_table:///SmartDashboard/Shooter_Temperature",
              "_title": "Temperature"
            }
          }
        }
      }
    }
  ],
  "windowGeometry": {
    "x": 0.0,
    "y": 0.0,
    "width": 1920.0,
    "height": 1040.0
  }
}